sphere_snap/__init__.py
sphere_snap/radial_distortion.py
sphere_snap/reprojections.py
sphere_snap/snap_config.py
sphere_snap/sphere_coor_projections.py
sphere_snap/sphere_snap.py
sphere_snap/top_view.py
sphere_snap/utils.py
sphere_snap-1.0.3.dist-info/LICENSE
sphere_snap-1.0.3.dist-info/METADATA
sphere_snap-1.0.3.dist-info/WHEEL
sphere_snap-1.0.3.dist-info/top_level.txt
sphere_snap-1.0.3.dist-info/RECORD
