Metadata-Version: 2.1
Name: sphere-snap
Version: 1.0.3
Summary: A quick and easy to use library for reprojecting various image types
Home-page: https://github.com/androclassic/SphereSnap
Author: Andrei Georgescu
Author-email: andrei.georgescu@yahoo.com
License: MIT License
Platform: UNKNOWN
Classifier: Development Status :: 2 - Pre-Alpha
Classifier: Intended Audience :: Science/Research
Classifier: License :: OSI Approved :: MIT License
Classifier: Operating System :: POSIX :: Linux
Classifier: Programming Language :: Python :: 3
Classifier: Programming Language :: Python :: 3.4
Classifier: Programming Language :: Python :: 3.5
Classifier: Topic :: Scientific/Engineering :: Image Processing
Requires-Dist: scipy (>=1.5.1)
Requires-Dist: opencv-python
Requires-Dist: matplotlib
Requires-Dist: numpy
Requires-Dist: logging
